MANIFEST.in
README.rst
requirements.txt
setup.py
telegraphy/__init__.py
telegraphy/utils.py
telegraphy.egg-info/PKG-INFO
telegraphy.egg-info/SOURCES.txt
telegraphy.egg-info/dependency_links.txt
telegraphy.egg-info/not-zip-safe
telegraphy.egg-info/requires.txt
telegraphy.egg-info/top_level.txt
telegraphy/contrib/__init__.py
telegraphy/contrib/django_telegraphy/__init__.py
telegraphy/contrib/django_telegraphy/events.py
telegraphy/contrib/django_telegraphy/models.py
telegraphy/contrib/django_telegraphy/settings.py
telegraphy/contrib/django_telegraphy/tests.py
telegraphy/contrib/django_telegraphy/urls.py
telegraphy/contrib/django_telegraphy/views.py
telegraphy/contrib/django_telegraphy/management/__init__.py
telegraphy/contrib/django_telegraphy/management/commands/__init__.py
telegraphy/contrib/django_telegraphy/management/commands/run_telegraph.py
telegraphy/contrib/django_telegraphy/management/commands/trunserver.py
telegraphy/contrib/django_telegraphy/static/telegraphy/img/logo.png
telegraphy/contrib/django_telegraphy/static/telegraphy/js/autobahn.js
telegraphy/contrib/django_telegraphy/static/telegraphy/js/autobahn.min.js
telegraphy/contrib/django_telegraphy/static/telegraphy/js/telegraphy.js
telegraphy/contrib/django_telegraphy/templates/django_telegraphy/telegraphy_scripts.html
telegraphy/contrib/django_telegraphy/templatetags/__init__.py
telegraphy/contrib/django_telegraphy/templatetags/telegraphy_tags.py
telegraphy/gateway/__init__.py
telegraphy/gateway/base.py
telegraphy/gateway/client.py
telegraphy/gateway/decorators.py
telegraphy/gateway/txwamp.py